sinapsis_generic_data_tools/__init__.py
sinapsis_generic_data_tools/helpers/__init__.py
sinapsis_generic_data_tools/helpers/audio_encoder.py
sinapsis_generic_data_tools/helpers/encode_img_base64.py
sinapsis_generic_data_tools/helpers/file_downloader.py
sinapsis_generic_data_tools/helpers/image_color_space_converter_cv.py
sinapsis_generic_data_tools/helpers/image_color_space_converter_torch.py
sinapsis_generic_data_tools/helpers/tags.py
sinapsis_generic_data_tools/templates/__init__.py
sinapsis_generic_data_tools/templates/image_color_conversion_np.py
sinapsis_generic_data_tools/templates/mask_non_roi.py
sinapsis_generic_data_tools/templates/packet_buffer_queue.py
sinapsis_generic_data_tools/templates/source_history_aggregator.py
sinapsis_generic_data_tools/templates/text_content_filter.py
sinapsis_generic_data_tools-0.1.11.dist-info/licenses/LICENSE
sinapsis_generic_data_tools-0.1.11.dist-info/METADATA
sinapsis_generic_data_tools-0.1.11.dist-info/WHEEL
sinapsis_generic_data_tools-0.1.11.dist-info/top_level.txt
sinapsis_generic_data_tools-0.1.11.dist-info/RECORD
