Metadata-Version: 2.4
Name: sinapsis-generic-data-tools
Version: 0.1.11
Summary: Collection of generic data tools
Author-email: SinapsisAI <dev@sinapsis.tech>
Project-URL: Homepage, https://sinapsis.tech
Project-URL: Documentation, https://docs.sinapsis.tech/docs
Project-URL: Tutorials, https://docs.sinapsis.tech/tutorials
Project-URL: Repository, https://github.com/Sinapsis-AI/sinapsis-data-tools.git
Requires-Python: >=3.10
License-File: LICENSE
Requires-Dist: requests>=2.32.3
Requires-Dist: sinapsis>=0.1.1
Provides-Extra: pillow
Requires-Dist: pillow>=11.2.1; extra == "pillow"
Provides-Extra: pydub
Requires-Dist: pydub>=0.25.1; extra == "pydub"
Provides-Extra: all
Requires-Dist: sinapsis-generic-data-tools[cv2,numpy,pillow,pydub,torch]; extra == "all"
Provides-Extra: cv2
Requires-Dist: opencv-python-headless>=4.11.0.86; extra == "cv2"
Provides-Extra: torch
Requires-Dist: torch>=2.5.1; extra == "torch"
Provides-Extra: numpy
Requires-Dist: numpy>=1.26.4; extra == "numpy"
Dynamic: license-file
